yaccounts_wd/__init__.py
yaccounts_wd/account.py
yaccounts_wd/chrome.py
yaccounts_wd/cli.py
yaccounts_wd/config.py
yaccounts_wd/payroll.py
yaccounts_wd/run_report.py
yaccounts_wd/table.py
yaccounts_wd/yutils.py
yaccounts_wd-1.0.0.dist-info/METADATA
yaccounts_wd-1.0.0.dist-info/WHEEL
yaccounts_wd-1.0.0.dist-info/entry_points.txt
yaccounts_wd-1.0.0.dist-info/top_level.txt
yaccounts_wd-1.0.0.dist-info/RECORD
