Metadata-Version: 2.4
Name: yaccounts-wd
Version: 1.0.0
Summary: Package for generating accounting reports from BYU's workday system.
Author-email: Jeff Goeders <jgoeders@byu.edu>
Requires-Dist: requests>=2.32.3
Requires-Dist: bs4>=0.0.2
Requires-Dist: selenium>=4.33.0
Requires-Dist: webdriver-manager>=4.0.2
Requires-Dist: pyyaml>=6.0.2
Requires-Dist: pandas>=2.2.3
Requires-Dist: openpyxl>=3.1.5
Requires-Dist: appdirs>=1.4.4
